lumix_upnp_dump.py
lumix_upnp_dump-0.1.0.dist-info/METADATA
lumix_upnp_dump-0.1.0.dist-info/WHEEL
lumix_upnp_dump-0.1.0.dist-info/entry_points.txt
lumix_upnp_dump-0.1.0.dist-info/RECORD
