Metadata-Version: 2.1
Name: lumix-upnp-dump
Version: 0.1.0
Summary: Program that dumps media from Lumix cameras on the network, removing them from device.
Home-page: https://github.com/klausweiss/lumix-upnp-dump
License: GPL-3.0-only
Author: Mikołaj Biel
Author-email: lumix-upnp-dump@mbiel.pl
Requires-Python: >=3.10.10,<3.12
Classifier: License :: OSI Approved :: GNU General Public License v3 (GPLv3)
Classifier: Programming Language :: Python :: 3
Classifier: Programming Language :: Python :: 3.11
Classifier: Topic :: Multimedia :: Graphics :: Capture :: Digital Camera
Requires-Dist: configargparse (>=1.5.3,<1.6.0)
Requires-Dist: python-didl-lite (>=1.3.2,<1.4.0)
Requires-Dist: requests (>=2.31.0,<2.32.0)
Requires-Dist: upnpclient (>=1.0.3,<1.1.0)
Project-URL: Repository, https://github.com/klausweiss/lumix-upnp-dump
